LICENSE
README.md
setup.cfg
setup.py
datablob/__init__.py
datablob.egg-info/PKG-INFO
datablob.egg-info/SOURCES.txt
datablob.egg-info/dependency_links.txt
datablob.egg-info/requires.txt
datablob.egg-info/top_level.txt