Metadata-Version: 2.4
Name: datablob
Version: 0.1.0
Summary: Client for Updating a Simple Data Warehouse on Blob Storage
Home-page: https://github.com/gocarta/datablob
Download-URL: https://github.com/gocarta/datablob/tarball/download
Author: Daniel J. Dufour
Author-email: daniel.j.dufour@gmail.com
Keywords: data,python
Classifier: Development Status :: 4 - Beta
Classifier: Programming Language :: Python :: 3
Classifier: License :: CC0 1.0 Universal (CC0 1.0) Public Domain Dedication
Classifier: Operating System :: OS Independent
License-File: LICENSE
Requires-Dist: boto3
Dynamic: author
Dynamic: author-email
Dynamic: classifier
Dynamic: description
Dynamic: description-content-type
Dynamic: download-url
Dynamic: home-page
Dynamic: keywords
Dynamic: license-file
Dynamic: requires-dist
Dynamic: summary
